[{"id":0,"name":"Billy Lopez","age":31,"phone":"(342) 512-3221","image":"koala","phrase":"Va do zuvama hun mi nuh ogru hengi durpif ti asfe veh pasregem arorumza zu."},{"id":1,"name":"Minnie Powell","age":56,"phone":"(685) 262-4562","image":"penguin","phrase":"Bavuv ive miniaw miupseb rezfamvan tumeh hokmacve vatuzzat ho peuhuzu rejim me hucugzid ugewe niwpo."},{"id":2,"name":"Curtis Reese","age":26,"phone":"(225) 595-1670","image":"owl","phrase":"Ta kosvahec edozolsog di duv veru ino goncipwo gabbi im bulago kutunul ci homa vo."},{"id":3,"name":"Sue McDaniel","age":29,"phone":"(311) 422-2460","image":"raccoon","phrase":"Edutajonu ojujiw pe dompip zasu wes juhoveli vowwedde wugci cilsipa vizom uc sorjaseb wap ju."},{"id":4,"name":"Marion Wong","age":61,"phone":"(710) 751-9496","image":"koala","phrase":"Lucza waznise suhesise ucipo jemconku puj ojena ji gimguhobo vuphaat ozucaw vipot mur hakpezci ajo."},{"id":5,"name":"Minerva Perry","age":41,"phone":"(455) 512-3137","image":"cat","phrase":"Cuseozo ot ufomotsi dup gujfikbuc vu cew giguwu aroze di owif edicasuw emicaca navennas hotzana."},{"id":6,"name":"Matthew Williams","age":41,"phone":"(673) 663-6699","image":"koala","phrase":"Kek mo tef ag soz leuhahu ejozaag dec uj urezofa izesosid imvec ecilunsug lotfo va."},{"id":7,"name":"Lawrence Pearson","age":48,"phone":"(589) 303-3000","image":"dog","phrase":"Zos sizculiha fuw ajlaap obafu amo lufi tubir rupec cu ogreb tailu inatih am murim."},{"id":8,"name":"Lola Guzman","age":61,"phone":"(238) 867-6336","image":"lion","phrase":"Duztumo za sivjutra juhovi aluf du se udeeho li kajna kohma nafifpa vepo ma hizizimo."},{"id":9,"name":"Julia Cummings","age":28,"phone":"(647) 273-5871","image":"raccoon","phrase":"Cidam kedudav vewfac tod intuvki lehi oghop gekjezoh fe sa zamorfoz zoega to deja hiwe."},{"id":10,"name":"Tom Miller","age":25,"phone":"(461) 812-5830","image":"fox","phrase":"Uf pon wahduh hi akcohwaz wa suzaka joeheza isozivi liun mu ri ki pafhasma ifoilo."},{"id":11,"name":"Floyd Roberson","age":24,"phone":"(354) 691-9270","image":"raccoon","phrase":"Navo ribeiv nagsokwe ehhuw ol hum her sakeb nirtistid linos walmo kawot kifecul tomofmu bi."},{"id":12,"name":"Beulah Simmons","age":49,"phone":"(884) 578-3509","image":"raccoon","phrase":"Dilnip mac viwekpuj he dutheste zosuz ojowu zedmef hul aknujugi da bursoc womistov agada babe."},{"id":13,"name":"Emma Simon","age":63,"phone":"(955) 957-2100","image":"fox","phrase":"Epouceko bos mutep zancozew ogi zitu eczapvar jil wuf ro irveko ebeparnul okunehova ewaitualo zipovul."},{"id":14,"name":"Luis Bailey","age":52,"phone":"(226) 775-5259","image":"penguin","phrase":"Pepmom rap nisijgaw vejga cirihi ga jag utzol kifeob ije juja katac lofev ulo siol."},{"id":15,"name":"Kyle Smith","age":40,"phone":"(369) 560-7867","image":"fox","phrase":"Vaten ci hapfejise kowakbas wa gehowib ah rowwe pupevvac zusud wemru vevrekhac pontevu leboh obofezod."},{"id":16,"name":"Chad Hogan","age":32,"phone":"(473) 703-3795","image":"lion","phrase":"Se mifva sohkitjel zuv rugnit hajlezfe har pidkigsim iltuf ervi para kegpohik su jiod kudpuz."},{"id":17,"name":"Lula Pierce","age":63,"phone":"(225) 406-3587","image":"cat","phrase":"Zobfic cu zemeb fohla gocse jednek wasesfi cal fuinwi ragace ulacamu cumwutsu gehonehe ka digajtih."},{"id":18,"name":"Della Murray","age":57,"phone":"(619) 416-8307","image":"dog","phrase":"Poadu gi pizoit gam zig podaksu riugi cu non ve se gataab jiguka zarmafu joj."},{"id":19,"name":"Jerome Sutton","age":59,"phone":"(281) 755-3613","image":"sheep","phrase":"Iceis uw is zetje ni ojeidjec wo tef nup le ofza naepa cozzawbi fuc miecu."},{"id":20,"name":"Lloyd Fuller","age":31,"phone":"(374) 917-5882","image":"pig","phrase":"Padu nefmahbe vuf kes zeulelu biserera nime ilinu ehewo oli nisek re kokate cigkuj fun."},{"id":21,"name":"Della Duncan","age":26,"phone":"(933) 528-1518","image":"lion","phrase":"Owporer doso hukpok ape goftug acu vah ohezi epironiz mamukuga te semzanif biv zosgil iscej."},{"id":22,"name":"Theodore Steele","age":19,"phone":"(561) 551-6891","image":"fox","phrase":"Riz rogu sabun cegpoggo buutzar ku acoga rihmo odoleb mucnide wabmot ompehmi usabij tof dajnacbuz."},{"id":23,"name":"Jon Reed","age":18,"phone":"(211) 628-4669","image":"fox","phrase":"Cazumun odivadi toc ra wikioki focilewu di huumdic galef wi worieti coblal viluf mirar mi."},{"id":24,"name":"Bess Brown","age":45,"phone":"(958) 866-1802","image":"cat","phrase":"Focju betwavo cibemil ra du fuitnef rad ejitub zitfoz cifaviihi micodrad zo mez niam ce."},{"id":25,"name":"John Fitzgerald","age":38,"phone":"(539) 515-1339","image":"fox","phrase":"Bilafgul luzjizel panuklam ojowud ahajuzut fi itkarlac li tilasebuf wotibuud ruavcoj madza fit gilob zaviznes."},{"id":26,"name":"Micheal Baker","age":30,"phone":"(871) 850-2911","image":"raccoon","phrase":"Fa utsovpu adner wowkuc pugduuc wu zotebgo keprem oje kudowuwu otelvov le sa vajto rilvec."},{"id":27,"name":"Nannie Page","age":55,"phone":"(623) 691-2373","image":"raccoon","phrase":"Bektaos gejjefdu awapazka echeh rup pag vabsahbos geto lusi hob gagilzij ikad ori paasuwe um."},{"id":28,"name":"Ryan Wilkins","age":28,"phone":"(873) 955-4428","image":"koala","phrase":"On cu fur pijfehzuz ariotpo nesomhe tespu zamesah etfej zocuvbe wok jiv hutkabwem cenelet mim."},{"id":29,"name":"Celia Richards","age":57,"phone":"(817) 316-2340","image":"dog","phrase":"Ko getado eboru tuwsa fori muni lirhufi ajfov da ecgebri solih zo tigpajra zonku inusekir."},{"id":30,"name":"Michael Marshall","age":31,"phone":"(922) 895-7839","image":"dog","phrase":"Dieje povpew zesik ihalurlem ifsu silaod igcob fetgaca jag me ifpazaf peuhegew ulocecdi hu zijpu."},{"id":31,"name":"Sarah Taylor","age":40,"phone":"(622) 305-8724","image":"pig","phrase":"Mag ujzak lefhude ha haz erwoge uto nag fed heckaj tebis pelub jesi ro haku."},{"id":32,"name":"Martin Hopkins","age":32,"phone":"(807) 361-2734","image":"cat","phrase":"Re ugi bufoh juj buvin gajulew bepbodal voavugis zulumi hotzikfe utoeter gi li egeigi zabgi."},{"id":33,"name":"Maria Cain","age":25,"phone":"(754) 725-4678","image":"pig","phrase":"Iflazjom pehaket fajhisaf cotdakom vosabvem wowe rihozsa uzusoj uclijep kuzug mej aguvuzwa tuk wucunuciz urnonvoh."},{"id":34,"name":"Rosie Bowen","age":27,"phone":"(240) 532-9576","image":"koala","phrase":"Hofebo hij lo genivo ihicjew pepiufu fizbeznec le idu colopja zejoglo givuvrih ero meut lidpa."},{"id":35,"name":"Jim Patterson","age":36,"phone":"(441) 375-9564","image":"fox","phrase":"Zotjuf ileden ucuz tez abna edpe jogru fusara goud hizawrib buzrup ev kaf cervus tilid."},{"id":36,"name":"Jonathan Manning","age":45,"phone":"(464) 856-6076","image":"fox","phrase":"Pacciro ilma denujeput avo hualziv cuis nek im cozvodaj jeimein sucluflig oznavbe jifafhat jan egu."},{"id":37,"name":"Owen Tate","age":26,"phone":"(957) 454-7980","image":"fox","phrase":"Potvi waced en mi luv im wowubufo kokezew wunezo aj nehohumu me anisa pe supu."},{"id":38,"name":"Estelle Gardner","age":42,"phone":"(740) 749-4196","image":"fox","phrase":"Ogiugu milki taklaz hokuku es so kevuma ha vavzeedu mioskuh ritag zofwa ra kilej fukla."},{"id":39,"name":"Genevieve Cole","age":40,"phone":"(754) 832-2236","image":"raccoon","phrase":"Hejtife abo rowviz du ru zakiklu imzi haadiva tigvina caufi kek tucrieg umbo muh ola."},{"id":40,"name":"Keith Romero","age":46,"phone":"(425) 594-7793","image":"dog","phrase":"Ducegew peasse patsu ha lu igte def jat ibepumco na bawmu bagol gefvuta toebiguz witam."},{"id":41,"name":"Douglas Gutierrez","age":58,"phone":"(633) 480-6168","image":"cat","phrase":"Giw tu efuij nulhu id vidso ge ob ofnu cozcig cen juv eseete ar sear."},{"id":42,"name":"Madge Figueroa","age":62,"phone":"(412) 917-2716","image":"penguin","phrase":"Wombudbul tusnec peasu ma gulutaza siza coznubgo kemic tore fi fahijo cihudvis feotru je meh."},{"id":43,"name":"Darrell White","age":36,"phone":"(465) 849-8516","image":"pig","phrase":"Etaeve jommani cisepe rosasfe avusu cajimibik puobirig defat zutrem jilsa coge awhe kuvsoru epko biddav."},{"id":44,"name":"Chris Fitzgerald","age":35,"phone":"(301) 734-4854","image":"dog","phrase":"Ta ibuuv faphinca oba lov fonika hugpad onve ed ab uwfuj urfav gimzawhuf hifiwac fut."},{"id":45,"name":"Benjamin May","age":43,"phone":"(524) 202-7473","image":"pig","phrase":"Sujpokkig nauz pocufon bijoza faviwgi te eji zu ropiv hub rupma vi ditow uhi juh."},{"id":46,"name":"Connor Barber","age":59,"phone":"(230) 209-5602","image":"cat","phrase":"Hu mobe co bica eptupon obakan cevogdo iva tatdundil wovvaplod tulum pi ho nar loit."},{"id":47,"name":"Johnny Hunter","age":61,"phone":"(227) 834-2985","image":"owl","phrase":"Et ephonra onwi hohvukej se fifafiku ufuso saknarele mok danva kuw den fojno fe we."},{"id":48,"name":"Jack Williamson","age":57,"phone":"(603) 450-5315","image":"penguin","phrase":"Pam comibi iwosus utto lutu fajikiod gacton ajeman va nebvijoc saune ispijol meh cam cufebdo."},{"id":49,"name":"Isabella Barnett","age":27,"phone":"(479) 309-8125","image":"cat","phrase":"Tud miwma had riz kis kikpisu kodur keror ise viwmu leju natopa capvag ojoma bihimsi."},{"id":50,"name":"Zachary Ward","age":60,"phone":"(924) 311-3816","image":"dog","phrase":"Dumov banfi fe le ji dol jup woc ka zevo rifbeze udivel tahzesi def nizobad."},{"id":51,"name":"Ian Pope","age":58,"phone":"(854) 296-4641","image":"fox","phrase":"Ucuzuen lihoen balo jef pimme lotaco esawig ro nedsi pufko hennusil kilkijef wu paojtaw fa."},{"id":52,"name":"Jeanette McBride","age":46,"phone":"(855) 570-5826","image":"cat","phrase":"Zaedabuh gok zoronkav sine kuz ika jirrin pur ewmu cansam nizahavul haneav kavu riowufez bobicos."},{"id":53,"name":"Rosetta Powell","age":52,"phone":"(445) 447-7477","image":"cat","phrase":"Odmu dibimle ujueflap efeija hizfe zi kolleve jof dec cueb depfew opihaswa ho zez omwo."},{"id":54,"name":"Charles Powell","age":51,"phone":"(678) 446-5039","image":"koala","phrase":"Bucen fonijfer poakibi jidalmu tu ludow himloaj tievelo egootu mudne gede ifhu vehutku miassog seta."},{"id":55,"name":"Landon Caldwell","age":25,"phone":"(430) 299-5145","image":"fox","phrase":"Poni bog eruubiha buma lufiide vet mok wijo hewtogcu sinawu gigcowriz kodwegaw vu hanaca sehpeewe."},{"id":56,"name":"Rhoda Santiago","age":46,"phone":"(870) 724-6908","image":"fox","phrase":"Wubmos vifmuzmal ripwulo jev he hav ogugeefi olakuov ube co pis apzolla ligsib iptecre cus."},{"id":57,"name":"Cody Clark","age":61,"phone":"(419) 708-5813","image":"sheep","phrase":"Ehu marnuz lawu woofiuc lundor woksoc towtip to merepes vonil ona ud cicbaz vetesgu aju."},{"id":58,"name":"Eddie Hopkins","age":52,"phone":"(858) 555-7729","image":"penguin","phrase":"Jovli forufzuv eronize dirfew jo rahsu zuvim hig eciaju vindic hagalwof met dunav edi huzob."},{"id":59,"name":"Jackson Colon","age":60,"phone":"(211) 312-9064","image":"penguin","phrase":"Wiboc ri cep huhup wa viv hes akwoit agkid zacki jamewde ral ide fe ak."},{"id":60,"name":"Donald Cole","age":26,"phone":"(784) 606-8703","image":"dog","phrase":"Ip hel reujetug ag at zujpes ocoacjac bovuwo pi sovojam bugiico wop ti tegabfa lavmil."},{"id":61,"name":"Willie Page","age":44,"phone":"(712) 208-7500","image":"penguin","phrase":"Ge dirmo ezuupa balofhe bedru bur ka nunbi fi pi hidvufe je mesoer wa moghef."},{"id":62,"name":"Wesley Frank","age":24,"phone":"(432) 649-4668","image":"pig","phrase":"Fezlumha kifpoclo upbor rah cuz mererev aviwaobo mi luzepe dovapnoh ebe muko nacat zococu gevpuaro."},{"id":63,"name":"Isabelle Floyd","age":31,"phone":"(958) 562-7460","image":"koala","phrase":"Sacur femvugcig ka du da ur ho feipeah cire itu ma bunivah dicib uciwu sub."},{"id":64,"name":"Luella Keller","age":23,"phone":"(246) 601-5993","image":"raccoon","phrase":"Bojniko butbof wafep nortola mibfe deza cojeb risano taodi wundijib gajek zusu atja eg kignaze."},{"id":65,"name":"Jeffery Vega","age":48,"phone":"(950) 497-4262","image":"koala","phrase":"Dikgo fisedi gof pusok ufa awhari ecozec coave giahe wo evpeg muwabre nadnopjab vereji ip."},{"id":66,"name":"Fred Arnold","age":18,"phone":"(288) 987-9861","image":"lion","phrase":"Waapira gifizerev mecelog wepunul ku ziv se dop zuvhagig culahid vina cab tifku oviamlot kehif."},{"id":67,"name":"Harry Gibbs","age":41,"phone":"(443) 255-2666","image":"koala","phrase":"Ewiucuko vud ado vidaha usma bazimic rerjin sarno suderfis azdandam bajovpu rom logul kop egiga."},{"id":68,"name":"Caleb Cooper","age":45,"phone":"(418) 734-8618","image":"pig","phrase":"Igepo jecuwemin medih ovu uzoze el pu zurduc ulesuogu beg ire mit ujoware gudvec megvoroc."},{"id":69,"name":"Andrew Klein","age":44,"phone":"(852) 859-8734","image":"penguin","phrase":"Vekfegcac sid sagkekol sin wiazbog aljiaw tezpeg bedvej ot le ha neted neerozec ma ujesudme."},{"id":70,"name":"Cordelia Bailey","age":18,"phone":"(751) 953-2379","image":"fox","phrase":"Fe ujpir oso riah ido bissecer zi wec mu wedbovo zajcica pilwigpu ogo wola gilve."},{"id":71,"name":"Rose Little","age":58,"phone":"(468) 623-2197","image":"lion","phrase":"Ri gugizi lazumkug sebka cafih peznehri vab oza kaf wopawtol rinopkoj dotseup zup etzalate mucsucef."},{"id":72,"name":"Cynthia Swanson","age":58,"phone":"(735) 983-6759","image":"owl","phrase":"Ozagoma ow licinabe jecu inpuhkum zumjuv iheufo uprejvo fi fici haov licoer nipus pul iju."},{"id":73,"name":"Lida McKinney","age":41,"phone":"(413) 692-7269","image":"cat","phrase":"Saris zokevkup ercomjo itkok cicucaw omi un kesfihfes koucapa ad nud teseg veb zo fowro."},{"id":74,"name":"Don Brown","age":53,"phone":"(901) 983-9437","image":"dog","phrase":"Ru ken jempuhke bej wadvo jec limdivo viwduntoh el biwri se je meoh je ih."},{"id":75,"name":"Jayden Harris","age":53,"phone":"(621) 381-4343","image":"owl","phrase":"Gaop jukum riawlag gus totod kabmif bievu bimipuvu uj cuw opcej odde zemuduz no pawapij."},{"id":76,"name":"Ann Waters","age":65,"phone":"(428) 786-3892","image":"penguin","phrase":"Ovuala fuzoavu wudbured no ja pohma codfod vocta ja coh kuzpok ludroggu nogwu beebime poz."},{"id":77,"name":"Jeffery French","age":59,"phone":"(784) 631-1336","image":"raccoon","phrase":"Ja ibu ha tame kowe zognakleg cojaju pa zane mev pebif fup nu du cukigifo."},{"id":78,"name":"Bradley Gregory","age":21,"phone":"(929) 998-3746","image":"pig","phrase":"Nom fomge sar fetew nujdi dotinow opned rover utrebpa binicu pugboldi vikpuk avjoec noeje rebupo."},{"id":79,"name":"Eugene Adkins","age":50,"phone":"(557) 462-8802","image":"cat","phrase":"Vov keh je foknuino okizufab emapa he agake inu pe an ru wegovur zofegam ecced."},{"id":80,"name":"Elnora Owens","age":48,"phone":"(739) 512-5025","image":"lion","phrase":"Vope rakgassiz bocapeset uroew mavohu vesbidil pikefe af wag vaplubbi ragco win he foaj ca."},{"id":81,"name":"Connor Gray","age":65,"phone":"(934) 987-5742","image":"lion","phrase":"Jahelu gacotwit kupbuc him mabpob ekuum totefi bektaw feemse owet radvawwuc telu sizansu hanfezuki nih."},{"id":82,"name":"Mable Schmidt","age":28,"phone":"(504) 692-1205","image":"sheep","phrase":"Verac izbeod hi owugociw daf okiaw wunhi voude zamdimhe det agohi gowi bihasfoh orzawuh tawiwek."},{"id":83,"name":"Justin Ramos","age":49,"phone":"(543) 713-3609","image":"koala","phrase":"Tivjezlot ewi iceuce de gihotrol lomeri muhta roeh ruurcaw juwap aftujjar zako opogo boabo rimjifner."},{"id":84,"name":"Polly Moss","age":31,"phone":"(700) 252-6468","image":"raccoon","phrase":"Fisuntot tawoba gihhek peal car juajte pujcecan dowedepu hiekoaz cokzuzi zu fa siksuzu ek mop."},{"id":85,"name":"Theresa Rodgers","age":52,"phone":"(473) 354-5028","image":"owl","phrase":"Nid atogidit men ubo nudfos bijewew fehhuz pabo huvisik kituja budog wihkod vohpawdiv bu fochi."},{"id":86,"name":"Jane Stewart","age":32,"phone":"(959) 826-6889","image":"cat","phrase":"Enmi div zulul vikojla tusceme hudohuk utavakij nopedle ud ehomigsev do remol vefkek kobjemhic salni."},{"id":87,"name":"Leah Taylor","age":58,"phone":"(954) 276-8680","image":"pig","phrase":"Mioca oseditfe ra tahgo bunam ti fad ij ja del pu fu vit wihu du."},{"id":88,"name":"Amelia Bush","age":39,"phone":"(467) 206-2235","image":"penguin","phrase":"Bad dirsakeg vagbes behpokipa me fenjaus supged wikdugen zawwicit da wasnopir jiwilpev to sucac bij."},{"id":89,"name":"Marie Roberson","age":42,"phone":"(619) 609-5498","image":"penguin","phrase":"Ma bibofbo deb ba ki huf ro himze araulgen jelhuk jovoddob kozetef segtidut morab niik."},{"id":90,"name":"Hilda Ford","age":36,"phone":"(642) 891-4562","image":"raccoon","phrase":"Wilo awezuchi ewnet re hukgufja zubees uvuocfaf se ujabapko wolu halguzo cimminval tu nahon zol."},{"id":91,"name":"Ricardo Gonzales","age":34,"phone":"(816) 265-7588","image":"cat","phrase":"Vik iv juwolu hebjijfif zevwif vogun waw vudku sekokunu nepbafer atlaf zeleco bokmo igurudam heedi."},{"id":92,"name":"Dollie Hardy","age":60,"phone":"(431) 396-8509","image":"raccoon","phrase":"Gah lounuite gukdeme rak azu sicelar weil ledom sukapze notade javzar kuw jam ve fud."},{"id":93,"name":"Jeff Cortez","age":43,"phone":"(440) 422-4475","image":"koala","phrase":"Tepjed luavhas sode fenomup hihsop kulma owiaficet vop zonoj ohi azegced zeadade how bapanow liprekir."},{"id":94,"name":"Sam Clayton","age":32,"phone":"(727) 965-7230","image":"raccoon","phrase":"Vavfit vo muwe buppotuv potten tew morvom ajvekjoz loja sewavsu owapi mepra latamot ve mu."},{"id":95,"name":"George Ramsey","age":50,"phone":"(612) 220-9640","image":"sheep","phrase":"Jelnekbac mok okgigew wopi kefbi dolek hiccu gi ahgij vehfodov lavpebal vukunive apekutgi rijopo mu."},{"id":96,"name":"Callie Klein","age":36,"phone":"(254) 580-1925","image":"raccoon","phrase":"Hosdif zik nih cowzed jekerfiv daisabe ihuubnup joliw tadekne hat nuhenbe fitrodiz bi nanwifzuz saloppa."},{"id":97,"name":"Shane Hampton","age":23,"phone":"(843) 557-7269","image":"raccoon","phrase":"Mek zif degala ip ufa wokuika roj hikfirwah vadip lohev zukbiez dijep ceriz vupcomta fomninnaw."},{"id":98,"name":"Willie Robinson","age":42,"phone":"(219) 460-9950","image":"dog","phrase":"Puhcedso domefnub bad weser vagsamu sal ugi we loenwig mobudowa luelihar lesano eba cu hubugib."},{"id":99,"name":"Jose Sandoval","age":65,"phone":"(230) 701-9139","image":"sheep","phrase":"Ujnih wuwajlu jiwoda sobre rahsamfaf cavcu geafu mebezkat lep owmab wuzet vahpeler dehlagmo an jood."},{"id":100,"name":"Darrell Ferguson","age":53,"phone":"(560) 811-9479","image":"owl","phrase":"Cegwul deadod zorzikap kakwap zoerbim cerura kitu sedpak pim mevgupo jiubaki pemar zeroh amuhe bodur."},{"id":101,"name":"Olive Dixon","age":29,"phone":"(858) 380-5911","image":"penguin","phrase":"Ti orsegif nuimueko tas jilhad pufofil wu kibodut fu pogtitepu gonfo dumlowve luto secjuhimu zanuz."},{"id":102,"name":"Steve Hudson","age":33,"phone":"(885) 266-1505","image":"dog","phrase":"Wesjigma reebe wof vuiz ibi wigma nofuvo ce gouc no kicka wocga isaka ivuveiro edcic."},{"id":103,"name":"Devin Henry","age":59,"phone":"(457) 966-3625","image":"dog","phrase":"Genapcez jamuh idace orsohfud la dodtu kadgiw ubeoce nuuw ehmew ifefal jese mojfiome bujokra obom."},{"id":104,"name":"Floyd Castillo","age":23,"phone":"(488) 877-6192","image":"fox","phrase":"Vohijo febu cesip miwifa avovihnir dinves ifpe udagefhav kij hu sovpefi upzunda fofciwdes fe ju."},{"id":105,"name":"Paul Valdez","age":60,"phone":"(351) 562-4478","image":"pig","phrase":"Gep eropi vuewluc danmosbo cibejet voebpi kelic jadidwe mi kemza fa tewmo raamomil vo wah."},{"id":106,"name":"Victor Pratt","age":50,"phone":"(343) 930-1589","image":"dog","phrase":"Rampov pim asu san eha zuhceza viuzone gaj nusik ju abijosi wijar suroz duba ecimimeb."},{"id":107,"name":"Alex Warren","age":22,"phone":"(519) 385-6936","image":"penguin","phrase":"Mavmilho famujeki suz awu fudopuf kuvfubmi puj lep ku ev se ih iropo erage ib."},{"id":108,"name":"Julian Dawson","age":33,"phone":"(765) 975-7408","image":"raccoon","phrase":"Eg gifmaob no jeelpe veza fulpocduj fogpi cul up gapan lu aduhiga monub uhihe awuba."},{"id":109,"name":"Dorothy Pratt","age":43,"phone":"(721) 652-8758","image":"sheep","phrase":"Usi gelum kewma najgoczi diaf roswedgi tudimedu opidu lahovzi codo detvec sozut fi cut magzavru."},{"id":110,"name":"Amy Dean","age":25,"phone":"(535) 728-4676","image":"lion","phrase":"Orsi bifap toc ewero bibrimma ifni kohiz fofa ugsitil ovrap hujwof dok fof jevhac sek."},{"id":111,"name":"Lora Jensen","age":53,"phone":"(954) 472-1392","image":"dog","phrase":"Binfodawi fet ra muves vif ukbicos biv gez utuero ebogoda if ji sukdota dah izu."},{"id":112,"name":"Jennie Matthews","age":24,"phone":"(666) 902-2659","image":"dog","phrase":"Ficte vuludkap nihefdag ogegiptes juzolbis uvta up pekemep nead oc wi wu haig runog daanzag."},{"id":113,"name":"Wayne Phelps","age":62,"phone":"(857) 765-6859","image":"cat","phrase":"Fotumsal fiero et ga haru ni tod tatbaj ceficmob vase wipebu neag ku no saj."},{"id":114,"name":"Ethel Flores","age":34,"phone":"(819) 528-3415","image":"owl","phrase":"Mevcuz pit raucuat bulac remsub pundokim sobse puhah revpir eveoscom muf heulsem ichocko neek ahloh."},{"id":115,"name":"Nell Glover","age":22,"phone":"(549) 283-4569","image":"sheep","phrase":"Pasas tusonez vego pe tas mut vuvag iduic funwipi jezsa gaknor mooraj pi ge narfo."},{"id":116,"name":"Joe Harrison","age":63,"phone":"(457) 576-8106","image":"lion","phrase":"Errojva ucoge kusobbe luhcik idre zoejpec dilefu zokbofof keasru ka boklupac denub kuwwa nub meaz."},{"id":117,"name":"Mina Garza","age":58,"phone":"(846) 585-6054","image":"pig","phrase":"Jobmonev za anonug naijaov zojmoccos job ved na uloduwme vepi burjo lon ejaezi lolrubup kog."},{"id":118,"name":"Louis Cole","age":31,"phone":"(256) 919-9393","image":"pig","phrase":"Zibroed bajzuw daf lu gon osounivu wig dim cavus zugdow jeheb ufmituz povlavone dowmagif edimafig."},{"id":119,"name":"Aiden Bishop","age":47,"phone":"(584) 883-9132","image":"penguin","phrase":"Lolahozo ronpoagi esuohpag wekvih pihohvep kirhabun cacefid adovena guj uja rup vu fejeegi sef lapahi."},{"id":120,"name":"Ellen Rice","age":52,"phone":"(603) 373-8335","image":"sheep","phrase":"Vorop iteje joz jibrurig mokoh muecijat kum siwmega jo mamnob kivusse ajo ferreg fe ev."},{"id":121,"name":"Esther Johnson","age":54,"phone":"(575) 604-7664","image":"cat","phrase":"Ide gopna ateuh irfutic vifujvan ponwu tupducmaf duvev funa peg calat etazulgew juczoz so pe."},{"id":122,"name":"Randy Watts","age":54,"phone":"(478) 864-7652","image":"fox","phrase":"Awbotnu kozik rujveser ugaw fiabe wir go javcan tin nadbapuve awduw gal ge hidme za."},{"id":123,"name":"James McKinney","age":64,"phone":"(434) 821-6581","image":"cat","phrase":"Rombigkan caesuik bi cujamiz sibis rel mizerek ivlihbe lam kunes wen jattibbob duhjenfus vujnalep de."},{"id":124,"name":"Loretta Stone","age":56,"phone":"(940) 701-7903","image":"owl","phrase":"Obo abekobom sapa budboteb zeh hu azloejo if wakgis cemmiw doolmi tapsevote ja eloosaib uvsuhid."},{"id":125,"name":"Ella Woods","age":61,"phone":"(716) 915-5466","image":"penguin","phrase":"Moj gomup sis lefzuh kic so emukni ikemo loero rajnode naec rebwabfu nu ipu gauffo."},{"id":126,"name":"Matthew Massey","age":46,"phone":"(637) 899-4424","image":"koala","phrase":"Betboh kewole heavi cisfite bucvu koaporeb latirwa nobusma du zefu tahdu va ne edu hasguczu."},{"id":127,"name":"Winnie Sanchez","age":51,"phone":"(666) 469-1540","image":"cat","phrase":"Karlevaz vev kih men pe ijete uju fabir vecunmuv sa ze we do cizul lu."},{"id":128,"name":"Cynthia Weaver","age":46,"phone":"(710) 249-9450","image":"koala","phrase":"Nenokkub efe siva ka rippud inireg pig iseot zahbuw aba kelahe siumi zuednim cu mukan."},{"id":129,"name":"Austin Houston","age":37,"phone":"(212) 501-8999","image":"fox","phrase":"Nic siifen wokrub jun corlap dizube ij go icahante ovwojwa weguso wuw nabfo wejwuivo vevivgu."},{"id":130,"name":"Roy Miller","age":60,"phone":"(453) 328-7576","image":"dog","phrase":"Tasbamba atzamwul zanil fah samerav ro zim wadic game kacza lupenci ob socwumeme gomejoni anonokwec."},{"id":131,"name":"Ola Shaw","age":29,"phone":"(637) 659-4755","image":"koala","phrase":"Vakpuh dak lovozka toc kassensa wodrug akogeode gumwan be vujdoffo wa ome diw duvjef uhupubab."},{"id":132,"name":"Katharine Blake","age":27,"phone":"(705) 719-5716","image":"sheep","phrase":"Busoku gewso eci oz fagoj esilena zuhir ceetetic car roon wiw co afe ti dosgo."},{"id":133,"name":"Lucy Kim","age":48,"phone":"(714) 809-7034","image":"cat","phrase":"Web go ruti loned pib pehmi iduhemi racgag ni piuwuce fidgelad kopbej geg wehon wacolriw."},{"id":134,"name":"Samuel Holmes","age":40,"phone":"(768) 684-7543","image":"sheep","phrase":"Nasas niv ruma gin hudopa lab agolatdem favigpo hi tovu fa cesewed dusadvaj zizojoh ve."},{"id":135,"name":"Leon Potter","age":52,"phone":"(952) 735-5181","image":"fox","phrase":"Sakovciz tive gufreg do raw ransov ecidbe odehuv ecoiduweh rosi hari acre pefad ciliv altisce."},{"id":136,"name":"Hannah Carr","age":60,"phone":"(230) 315-6746","image":"dog","phrase":"Be litzemwu lujdinwa sig op wilmug emozev lapmo igjisbij lohidveg nub de zuak degos cite."},{"id":137,"name":"Bess Singleton","age":31,"phone":"(265) 392-7964","image":"dog","phrase":"Hikid lijic etofosap ginemo emeseh dajisda wezvulho irazi dibvow tav ivune uc bukcecpiw alucun wuli."},{"id":138,"name":"Leah Stevens","age":42,"phone":"(389) 584-4991","image":"dog","phrase":"Hac ok lunmege fuahicu peev dik ken rofim vaor wumewow vo revur tes jabuge git."},{"id":139,"name":"Ralph Chavez","age":40,"phone":"(216) 885-2165","image":"cat","phrase":"Epdan goduzoh wapun ziw opow epec donece howevbe deuvu rupunaowo vawotud men guteni zom so."},{"id":140,"name":"Lucille Perkins","age":53,"phone":"(233) 796-8054","image":"raccoon","phrase":"Bigib hokbe cofek tedud kel ce rimhuweg nehavak ebugojo rahpop bic fereem jadevap jourauf tosev."},{"id":141,"name":"Linnie Marshall","age":42,"phone":"(419) 327-2077","image":"koala","phrase":"Corlevu ritcucri tiseij lokap dizjamta gije fu fu wubijnu ke elovabuv kezetgi umzap gituj amiaga."},{"id":142,"name":"Darrell Taylor","age":60,"phone":"(262) 715-6855","image":"raccoon","phrase":"Se hodeve cijvez lijga zalopip jizkohok si he tumfova mu wir idpadmad rogdi fe luhbu."},{"id":143,"name":"Anne Buchanan","age":53,"phone":"(413) 738-2458","image":"koala","phrase":"Juokfa pod wawma lis ricavho ka korep apiwiju japep ew kaev busaz ci ra worag."},{"id":144,"name":"Dennis Nguyen","age":35,"phone":"(512) 436-8941","image":"fox","phrase":"Aze sa ceg ze uf fazzum be laggu po ruhep juz waar jihofwo jofasot te."},{"id":145,"name":"Emilie Riley","age":51,"phone":"(802) 247-7932","image":"penguin","phrase":"Somracis ivahemed dezeup ave mumor totuev kuverso gumakvuv opahow rofubzim bupzomov asu kezawihi domilzef mewunbu."},{"id":146,"name":"Cecelia Barrett","age":28,"phone":"(503) 260-5705","image":"owl","phrase":"Sew bom finusuc jeb cabujduk luwi tedpebhu cuj ci or komzovwu lewaze kavej oca weguzbo."},{"id":147,"name":"Scott Franklin","age":46,"phone":"(475) 877-6539","image":"raccoon","phrase":"Edrapu eg fuse tu di kaj hoiwug fotag lakotep pezucu aneje riogo ujinepuj ikdidat etasud."},{"id":148,"name":"Glenn Mitchell","age":47,"phone":"(837) 959-2704","image":"raccoon","phrase":"Po wesohib duhvame ciutuaso mitvelco juj retli jo ravuguh to folfirzu idicozeh nosgetcag doksu sumap."},{"id":149,"name":"Henrietta Lewis","age":42,"phone":"(217) 377-2905","image":"lion","phrase":"Elale cenev buvol luheuv basa zah apauzo vapma gepenkov zat pedgabbaz ezo en sac cuh."}]
